valyu_pipeline/__init__.py
valyu_pipeline/processor.py
valyu_pipeline/types/__init__.py
valyu_pipeline/types/upload_types.py
valyu_pipeline-0.0.26a0.dist-info/METADATA
valyu_pipeline-0.0.26a0.dist-info/WHEEL
valyu_pipeline-0.0.26a0.dist-info/top_level.txt
valyu_pipeline-0.0.26a0.dist-info/RECORD
