Metadata-Version: 2.1
Name: valyu-pipeline
Version: 0.0.26a0
Summary: A Python package for accessing the Valyu Data pipeline infrastructure
Author: Valyu.Network
Author-email: harvey@valyu.network
Classifier: Development Status :: 4 - Beta
Classifier: Intended Audience :: Science/Research
Classifier: License :: OSI Approved :: MIT License
Classifier: Programming Language :: Python :: 3.8
Requires-Python: >=3.8
Requires-Dist: requests
Requires-Dist: PyMuPDF
Requires-Dist: tqdm
Requires-Dist: Pillow
Requires-Dist: IPython
Requires-Dist: pydantic
